poetry_demo_james_moon/__init__.py
poetry_demo_james_moon-0.1.0.dist-info/WHEEL
poetry_demo_james_moon-0.1.0.dist-info/METADATA
poetry_demo_james_moon-0.1.0.dist-info/RECORD
